{"cameraMode":{"drawMode":0,"name":"Shaded","section":"Shading Mode"},"sceneLighting":true,"audioPlay":false,"sceneViewState":{"m_AlwaysRefresh":false,"showFog":true,"showSkybox":true,"showFlares":true,"showImageEffects":true,"showParticleSystems":true,"showVisualEffectGraphs":true,"m_FxEnabled":true},"in2DMode":false,"pivot":{"x":11.21636962890625,"y":4.452037334442139,"z":21.510507583618165},"rotation":{"x":-0.00877777487039566,"y":-0.989524781703949,"z":0.048060379922389987,"w":-0.1394849568605423},"size":17.32394027709961,"orthographic":false}